{
  "county": "嘉義市",
  "updated_at": "2026-07-23 01:09:12",
  "stations": [
    {
      "site_id": "42",
      "site_name": "嘉義",
      "county": "嘉義市",
      "aqi": 55,
      "status": "普通",
      "pollutant": "細懸浮微粒",
      "pm2_5": "12",
      "pm2_5_avg": "13.8",
      "pm10": "30",
      "pm10_avg": "33",
      "o3": "5",
      "o3_8hr": "18",
      "co": "0.13",
      "co_8hr": "0.1",
      "so2": "0.8",
      "so2_avg": "1",
      "no2": "4",
      "no": "1.1",
      "nox": "5.7",
      "wind_speed": "1.1",
      "wind_direc": "116",
      "longitude": "120.44125",
      "latitude": "23.464779",
      "publish_time": "2026/07/23 01:00:00"
    }
  ]
}