{
  "county": "嘉義縣",
  "updated_at": "2026-07-04 07:09:09",
  "stations": [
    {
      "site_id": "40",
      "site_name": "朴子",
      "county": "嘉義縣",
      "aqi": 40,
      "status": "良好",
      "pollutant": "",
      "pm2_5": "6",
      "pm2_5_avg": "9.9",
      "pm10": "23",
      "pm10_avg": "24",
      "o3": "6",
      "o3_8hr": "9",
      "co": "0.22",
      "co_8hr": "0.2",
      "so2": "0.6",
      "so2_avg": "1",
      "no2": "7",
      "no": "4",
      "nox": "11.6",
      "wind_speed": "1.1",
      "wind_direc": "114",
      "longitude": "120.2478",
      "latitude": "23.46538",
      "publish_time": "2026/07/04 07:00:00"
    },
    {
      "site_id": "39",
      "site_name": "新港",
      "county": "嘉義縣",
      "aqi": 48,
      "status": "良好",
      "pollutant": "",
      "pm2_5": "9",
      "pm2_5_avg": "10.1",
      "pm10": "33",
      "pm10_avg": "29",
      "o3": "11",
      "o3_8hr": "14",
      "co": "0.27",
      "co_8hr": "0.2",
      "so2": "2.1",
      "so2_avg": "1",
      "no2": "6",
      "no": "3.3",
      "nox": "9.7",
      "wind_speed": "0.4",
      "wind_direc": "332",
      "longitude": "120.34553",
      "latitude": "23.554838",
      "publish_time": "2026/07/04 07:00:00"
    }
  ]
}