{
  "county": "基隆市",
  "updated_at": "2026-07-12 02:09:10",
  "stations": [
    {
      "site_id": "1",
      "site_name": "基隆",
      "county": "基隆市",
      "aqi": 20,
      "status": "良好",
      "pollutant": "",
      "pm2_5": "3",
      "pm2_5_avg": "1.6",
      "pm10": "7",
      "pm10_avg": "3",
      "o3": "14",
      "o3_8hr": "22",
      "co": "0.13",
      "co_8hr": "0.1",
      "so2": "0.8",
      "so2_avg": "1",
      "no2": "2",
      "no": "1",
      "nox": "3.1",
      "wind_speed": "1",
      "wind_direc": "267",
      "longitude": "121.760056",
      "latitude": "25.129168",
      "publish_time": "2026/07/12 02:00:00"
    }
  ]
}