{
  "county": "彰化縣",
  "updated_at": "2026-07-14 07:09:11",
  "stations": [
    {
      "site_id": "139",
      "site_name": "員林",
      "county": "彰化縣",
      "aqi": 22,
      "status": "良好",
      "pollutant": "",
      "pm2_5": "9",
      "pm2_5_avg": "5.4",
      "pm10": "17",
      "pm10_avg": "10",
      "o3": "11",
      "o3_8hr": "18",
      "co": "0.2",
      "co_8hr": "0.1",
      "so2": "0.8",
      "so2_avg": "1",
      "no2": "5",
      "no": "2.2",
      "nox": "7.9",
      "wind_speed": "1.6",
      "wind_direc": "182",
      "longitude": "120.56319",
      "latitude": "23.961594",
      "publish_time": "2026/07/14 07:00:00"
    },
    {
      "site_id": "33",
      "site_name": "彰化",
      "county": "彰化縣",
      "aqi": 24,
      "status": "良好",
      "pollutant": "",
      "pm2_5": "6",
      "pm2_5_avg": "3.7",
      "pm10": "24",
      "pm10_avg": "13",
      "o3": "25",
      "o3_8hr": "26",
      "co": "0.16",
      "co_8hr": "0.1",
      "so2": "2.3",
      "so2_avg": "0",
      "no2": "5",
      "no": "2.1",
      "nox": "8",
      "wind_speed": "1.7",
      "wind_direc": "190",
      "longitude": "120.54152",
      "latitude": "24.066",
      "publish_time": "2026/07/14 07:00:00"
    },
    {
      "site_id": "85",
      "site_name": "大城",
      "county": "彰化縣",
      "aqi": 28,
      "status": "良好",
      "pollutant": "",
      "pm2_5": "8",
      "pm2_5_avg": "5.6",
      "pm10": "19",
      "pm10_avg": "17",
      "o3": "14",
      "o3_8hr": "17",
      "co": "0.12",
      "co_8hr": "0.1",
      "so2": "0.8",
      "so2_avg": "0",
      "no2": "3",
      "no": "2.6",
      "nox": "5.9",
      "wind_speed": "1.1",
      "wind_direc": "191",
      "longitude": "120.26964",
      "latitude": "23.85493",
      "publish_time": "2026/07/14 07:00:00"
    },
    {
      "site_id": "34",
      "site_name": "線西",
      "county": "彰化縣",
      "aqi": 29,
      "status": "良好",
      "pollutant": "",
      "pm2_5": "11",
      "pm2_5_avg": "7.1",
      "pm10": "21",
      "pm10_avg": "14",
      "o3": "8",
      "o3_8hr": "16",
      "co": "0.24",
      "co_8hr": "0.1",
      "so2": "1.4",
      "so2_avg": "0",
      "no2": "10",
      "no": "4",
      "nox": "14.6",
      "wind_speed": "2.2",
      "wind_direc": "183",
      "longitude": "120.46906",
      "latitude": "24.131672",
      "publish_time": "2026/07/14 07:00:00"
    },
    {
      "site_id": "35",
      "site_name": "二林",
      "county": "彰化縣",
      "aqi": 37,
      "status": "良好",
      "pollutant": "",
      "pm2_5": "9",
      "pm2_5_avg": "5.9",
      "pm10": "35",
      "pm10_avg": "22",
      "o3": "7",
      "o3_8hr": "10",
      "co": "0.2",
      "co_8hr": "0.1",
      "so2": "0.8",
      "so2_avg": "0",
      "no2": "6",
      "no": "2.6",
      "nox": "9.2",
      "wind_speed": "1",
      "wind_direc": "121",
      "longitude": "120.40965",
      "latitude": "23.925175",
      "publish_time": "2026/07/14 07:00:00"
    }
  ]
}