{
  "county": "新竹市",
  "updated_at": "2026-07-24 08:09:19",
  "stations": [
    {
      "site_id": "24",
      "site_name": "新竹",
      "county": "新竹市",
      "aqi": 63,
      "status": "普通",
      "pollutant": "細懸浮微粒",
      "pm2_5": "14",
      "pm2_5_avg": "17",
      "pm10": "32",
      "pm10_avg": "35",
      "o3": "14",
      "o3_8hr": "13",
      "co": "0.24",
      "co_8hr": "0.1",
      "so2": "1.6",
      "so2_avg": "15",
      "no2": "10",
      "no": "4.3",
      "nox": "14.4",
      "wind_speed": "1.2",
      "wind_direc": "241",
      "longitude": "120.97237",
      "latitude": "24.805635",
      "publish_time": "2026/07/24 08:00:00"
    }
  ]
}