{
  "county": "苗栗縣",
  "updated_at": "2026-07-06 16:09:15",
  "stations": [
    {
      "site_id": "27",
      "site_name": "三義",
      "county": "苗栗縣",
      "aqi": 31,
      "status": "良好",
      "pollutant": "",
      "pm2_5": "4",
      "pm2_5_avg": "5.7",
      "pm10": "13",
      "pm10_avg": "16",
      "o3": "34",
      "o3_8hr": "33",
      "co": "0.14",
      "co_8hr": "0.1",
      "so2": "2",
      "so2_avg": "1",
      "no2": "3",
      "no": "2",
      "nox": "5.9",
      "wind_speed": "2.8",
      "wind_direc": "232",
      "longitude": "120.75957",
      "latitude": "24.382484",
      "publish_time": "2026/07/06 16:00:00"
    },
    {
      "site_id": "25",
      "site_name": "頭份",
      "county": "苗栗縣",
      "aqi": 31,
      "status": "良好",
      "pollutant": "",
      "pm2_5": "0",
      "pm2_5_avg": "5.3",
      "pm10": "9",
      "pm10_avg": "18",
      "o3": "31",
      "o3_8hr": "33",
      "co": "0.08",
      "co_8hr": "0.1",
      "so2": "2.3",
      "so2_avg": "1",
      "no2": "1",
      "no": "1.3",
      "nox": "2.6",
      "wind_speed": "4.5",
      "wind_direc": "266",
      "longitude": "120.89869",
      "latitude": "24.696907",
      "publish_time": "2026/07/06 16:00:00"
    },
    {
      "site_id": "26",
      "site_name": "苗栗",
      "county": "苗栗縣",
      "aqi": 34,
      "status": "良好",
      "pollutant": "",
      "pm2_5": "2",
      "pm2_5_avg": "5.2",
      "pm10": "5",
      "pm10_avg": "11",
      "o3": "35",
      "o3_8hr": "37",
      "co": "0.08",
      "co_8hr": "0.1",
      "so2": "1.3",
      "so2_avg": "1",
      "no2": "2",
      "no": "1.9",
      "nox": "4.4",
      "wind_speed": "2.5",
      "wind_direc": "249",
      "longitude": "120.820114",
      "latitude": "24.564991",
      "publish_time": "2026/07/06 16:00:00"
    }
  ]
}